scrcpy/__init__.py
scrcpy/const.py
scrcpy/control.py
scrcpy/core.py
scrcpy/scrcpy-server.jar
scrcpy_ui/__init__.py
scrcpy_ui/main.py
scrcpy_ui/main.ui
scrcpy_ui/ui_main.py
scrcpy_client-0.4.7.dist-info/entry_points.txt
scrcpy_client-0.4.7.dist-info/LICENSE.txt
scrcpy_client-0.4.7.dist-info/WHEEL
scrcpy_client-0.4.7.dist-info/METADATA
scrcpy_client-0.4.7.dist-info/RECORD
