Metadata-Version: 2.1
Name: scrcpy-client
Version: 0.4.7
Summary: A client of scrcpy
Home-page: https://github.com/leng-yue/py-scrcpy-client
License: MIT
Author: lengyue
Author-email: lengyue@lengyue.me
Requires-Python: >=3.7,<3.11
Classifier: License :: OSI Approved :: MIT License
Classifier: Programming Language :: Python :: 3
Classifier: Programming Language :: Python :: 3.7
Classifier: Programming Language :: Python :: 3.8
Classifier: Programming Language :: Python :: 3.9
Classifier: Programming Language :: Python :: 3.10
Provides-Extra: ui
Requires-Dist: PySide6 (>=6.0.0,<7.0.0); extra == "ui"
Requires-Dist: adbutils (>=1.0.8,<2.0.0)
Requires-Dist: av (>=9.0.0,<10.0.0)
Requires-Dist: opencv-python (>=4.5.0,<5.0.0)
Project-URL: Repository, https://github.com/leng-yue/py-scrcpy-client
